studipy/__init__.py
studipy/browser.py
studipy/calendar.py
studipy/client.py
studipy/constants.py
studipy/courses.py
studipy/files.py
studipy/helper.py
studipy/messages.py
studipy/types.py
studipy/users.py
studipy-0.2.5.dist-info/LICENSE
studipy-0.2.5.dist-info/METADATA
studipy-0.2.5.dist-info/WHEEL
studipy-0.2.5.dist-info/RECORD
