Metadata-Version: 2.1
Name: studipy
Version: 0.2.5
Summary: studip python api using JSONAPI
Home-page: https://github.com/FrederikRichter/studipy
License: MIT
Author: Frederik Richter
Requires-Python: >=3.12,<4.0
Classifier: License :: OSI Approved :: MIT License
Classifier: Programming Language :: Python :: 3
Classifier: Programming Language :: Python :: 3.12
Requires-Dist: pip (>=24.2,<25.0)
Requires-Dist: pydantic (>=2.7.4,<3.0.0)
Requires-Dist: python-dotenv (>=1.0.1,<2.0.0)
Requires-Dist: requests (>=2.31.0,<3.0.0)
Project-URL: Repository, https://github.com/FrederikRichter/studipy
